ManongFanshenQuannianWenzhangJinghua2017/README.md
ManongFanshenQuannianWenzhangJinghua2017/__init__.py
ManongFanshenQuannianWenzhangJinghua2017/__main__.py
ManongFanshenQuannianWenzhangJinghua2017/file.epub
ManongFanshenQuannianWenzhangJinghua2017/index.html
ManongFanshenQuannianWenzhangJinghua2017/css/__init__.py
ManongFanshenQuannianWenzhangJinghua2017/css/annotations.css
ManongFanshenQuannianWenzhangJinghua2017/css/main.css
ManongFanshenQuannianWenzhangJinghua2017/css/normalize.css
ManongFanshenQuannianWenzhangJinghua2017/css/popup.css
ManongFanshenQuannianWenzhangJinghua2017/font/__init__.py
ManongFanshenQuannianWenzhangJinghua2017/font/fontello.eot
ManongFanshenQuannianWenzhangJinghua2017/font/fontello.svg
ManongFanshenQuannianWenzhangJinghua2017/font/fontello.ttf
ManongFanshenQuannianWenzhangJinghua2017/font/fontello.woff
ManongFanshenQuannianWenzhangJinghua2017/img/__init__.py
ManongFanshenQuannianWenzhangJinghua2017/img/annotator-glyph-sprite.png
ManongFanshenQuannianWenzhangJinghua2017/img/annotator-icon-sprite.png
ManongFanshenQuannianWenzhangJinghua2017/img/apple-touch-icon.png
ManongFanshenQuannianWenzhangJinghua2017/img/cancelfullscreen.png
ManongFanshenQuannianWenzhangJinghua2017/img/close.png
ManongFanshenQuannianWenzhangJinghua2017/img/fullscreen.png
ManongFanshenQuannianWenzhangJinghua2017/img/loader.gif
ManongFanshenQuannianWenzhangJinghua2017/img/menu-icon.png
ManongFanshenQuannianWenzhangJinghua2017/img/save.png
ManongFanshenQuannianWenzhangJinghua2017/img/saved.png
ManongFanshenQuannianWenzhangJinghua2017/img/settings-s.png
ManongFanshenQuannianWenzhangJinghua2017/img/settings.png
ManongFanshenQuannianWenzhangJinghua2017/img/star.png
ManongFanshenQuannianWenzhangJinghua2017/js/__init__.py
ManongFanshenQuannianWenzhangJinghua2017/js/epub.js
ManongFanshenQuannianWenzhangJinghua2017/js/epub.min.js
ManongFanshenQuannianWenzhangJinghua2017/js/epub.min.map
ManongFanshenQuannianWenzhangJinghua2017/js/hooks.min.js
manong_fanshen_quannian_wenzhang_jinghua_2017-2024.3.4.0.dist-info/METADATA
manong_fanshen_quannian_wenzhang_jinghua_2017-2024.3.4.0.dist-info/WHEEL
manong_fanshen_quannian_wenzhang_jinghua_2017-2024.3.4.0.dist-info/entry_points.txt
manong_fanshen_quannian_wenzhang_jinghua_2017-2024.3.4.0.dist-info/top_level.txt
manong_fanshen_quannian_wenzhang_jinghua_2017-2024.3.4.0.dist-info/RECORD
